[
    {
        "type": "小哈",
        "alt": "肉呼呼",
        "files": [
            {
                "md5": "20e29d4f0f76b608ef45103e3dcdff24",
                "ext": ".gif",
                "size": 31448,
                "alias": [
                    {
                        "md5": "6868a6234202c578b938496bfbe367ed",
                        "ext": ".png",
                        "size": 3377
                    },
                    {
                        "md5": "d13296a590ad4d350d5b5bfee504aa59",
                        "ext": ".png",
                        "size": 3859
                    }
                ]
            }
        ]
    },
    {
        "type": "小哈",
        "alt": "流口水",
        "files": [
            {
                "md5": "16020dfff8134183d7d58e5865417737",
                "ext": ".gif",
                "size": 23084,
                "alias": [
                    {
                        "md5": "9c18a6c833f8502ba8f0720b24fe81ab",
                        "ext": ".png",
                        "size": 4802
                    }
                ]
            }
        ]
    },
    {
        "type": "小哈",
        "alt": "饿死了",
        "files": [
            {
                "md5": "c9e3d8d43bd90b9143adac3066e3e18b",
                "ext": ".gif",
                "size": 11786,
                "alias": [
                    {
                        "md5": "2194be1138125bb76337cc16ece4bd94",
                        "ext": ".png",
                        "size": 5402
                    }
                ]
            }
        ]
    },
    {
        "type": "小哈",
        "alt": "大吃一斤",
        "files": [
            {
                "md5": "7096ec846052b74e62ba8c4ba0ff96f3",
                "ext": ".gif",
                "size": 13931,
                "alias": [
                    {
                        "md5": "6fd179078db13e131fa12d730dbc3b92",
                        "ext": ".png",
                        "size": 5625
                    }
                ]
            }
        ]
    },
    {
        "type": "小哈",
        "alt": "喜欢",
        "files": [
            {
                "md5": "f54263719c2e137c4169807cf32b8804",
                "ext": ".gif",
                "size": 27857,
                "alias": [
                    {
                        "md5": "1dffe4211609c773e7198aaa0a0c2927",
                        "ext": ".png",
                        "size": 6569
                    }
                ]
            }
        ]
    },
    {
        "type": "小哈",
        "alt": "吃东西",
        "files": [
            {
                "md5": "cb167cadf8b6c419b543f5773b11f577",
                "ext": ".gif",
                "size": 16770,
                "alias": [
                    {
                        "md5": "b0d28acc51a1df594d2f53b0c28b932f",
                        "ext": ".png",
                        "size": 4513
                    }
                ]
            }
        ]
    },
    {
        "type": "小哈",
        "alt": "吃汉堡",
        "files": [
            {
                "md5": "b395e93f07b6ba906d4e45672613b19b",
                "ext": ".gif",
                "size": 24911,
                "alias": [
                    {
                        "md5": "3591162e78a4afed4f79fb865de43f94",
                        "ext": ".png",
                        "size": 5583
                    }
                ]
            }
        ]
    },
    {
        "type": "小哈",
        "alt": "称体重",
        "files": [
            {
                "md5": "b4b2b751967737a5a08b885bb7d09304",
                "ext": ".gif",
                "size": 20067,
                "alias": [
                    {
                        "md5": "ee3e2d7b4914dd0635f6e77aa0fd3d81",
                        "ext": ".png",
                        "size": 4108
                    }
                ]
            }
        ]
    },
    {
        "type": "小哈",
        "alt": "健身",
        "files": [
            {
                "md5": "68c9b8a6e5a7ec339ac7b3f71b040732",
                "ext": ".gif",
                "size": 31051,
                "alias": [
                    {
                        "md5": "82c1b9ac9e50239d578953a896e7548f",
                        "ext": ".png",
                        "size": 3492
                    }
                ]
            }
        ]
    }
]